primus_safe_pulsekit/__init__.py
primus_safe_pulsekit/dsl/__init__.py
primus_safe_pulsekit/dsl/dsl.py
primus_safe_pulsekit/hardwareinfo/__init__.py
primus_safe_pulsekit/hardwareinfo/cpu.py
primus_safe_pulsekit/hardwareinfo/ethernet.py
primus_safe_pulsekit/hardwareinfo/gpu.py
primus_safe_pulsekit/hardwareinfo/hardware_info.py
primus_safe_pulsekit/hardwareinfo/memory.py
primus_safe_pulsekit/plugin/__init__.py
primus_safe_pulsekit/plugin/local_plugin.py
primus_safe_pulsekit/plugin/plugin.py
primus_safe_pulsekit/plugin/plugin_context.py
primus_safe_pulsekit/plugin/remote_plugin.py
primus_safe_pulsekit/server/__init__.py
primus_safe_pulsekit/server/runner.py
primus_safe_pulsekit/util/__init__.py
primus_safe_pulsekit/util/port.py
primus_safe_pulsekit/util/progress_reporter.py
primus_safe_pulsekit-0.1.2.dist-info/METADATA
primus_safe_pulsekit-0.1.2.dist-info/WHEEL
primus_safe_pulsekit-0.1.2.dist-info/top_level.txt
primus_safe_pulsekit-0.1.2.dist-info/RECORD
