Metadata-Version: 2.4
Name: primus-safe-pulsekit
Version: 0.1.2
Summary: Core of pulsekit
Requires-Python: >=3.10
Requires-Dist: fastapi>=0.115.12
Requires-Dist: psutil>=7.0.0
Requires-Dist: py-cpuinfo>=9.0.0
Requires-Dist: sse-starlette>=2.3.5
Requires-Dist: uvicorn>=0.34.2
